btframework/__init__.py
btframework/helpers.py
btframework/portfolio.py
btframework/trade.py
btframework-1.0.2.dist-info/METADATA
btframework-1.0.2.dist-info/WHEEL
btframework-1.0.2.dist-info/top_level.txt
btframework-1.0.2.dist-info/RECORD
