Metadata-Version: 2.1
Name: btframework
Version: 1.0.2
Summary: A simple backtesting library
Home-page: UNKNOWN
Author: Piyush Patil
Author-email: patilpiyush210@gmail.com
License: UNKNOWN
Platform: UNKNOWN
Classifier: Programming Language :: Python :: 3
Classifier: License :: OSI Approved :: MIT License
Classifier: Operating System :: OS Independent
Requires-Python: >=3.6
Requires-Dist: numpy
Requires-Dist: pandas
Requires-Dist: psycopg2-binary
Requires-Dist: pytz
Requires-Dist: ta
Requires-Dist: openpyxl
